tremexpresso/__init__.py
tremexpresso-0.0.0.dist-info/LICENSE
tremexpresso-0.0.0.dist-info/METADATA
tremexpresso-0.0.0.dist-info/WHEEL
tremexpresso-0.0.0.dist-info/top_level.txt
tremexpresso-0.0.0.dist-info/RECORD
